pathoplex/__init__.py
pathoplex-0.0.1.dist-info/LICENSE
pathoplex-0.0.1.dist-info/WHEEL
pathoplex-0.0.1.dist-info/METADATA
pathoplex-0.0.1.dist-info/RECORD
