Metadata-Version: 2.1
Name: pathoplex
Version: 0.0.1
Summary: A Python package for the analysis of spatially resolved proteomics data.
Author-email: Malte Kuehl <malte.kuehl@clin.au.dk>
Classifier: License :: OSI Approved :: GNU General Public License v3 or later (GPLv3+)
Project-URL: Home, https://complextissue.com
